spyder_remote_client/__init__.py
spyder_remote_client/constants.py
spyder_remote_client/discover.py
spyder_remote_client/utils.py
spyder_remote_client/spyder/__init__.py
spyder_remote_client/spyder/api.py
spyder_remote_client/spyder/container.py
spyder_remote_client/spyder/dialog.py
spyder_remote_client/spyder/discover.py
spyder_remote_client/spyder/plugin.py
spyder_remote_client/spyder/widgets.py
spyder_remote_client-0.0.4.dist-info/LICENSE.txt
spyder_remote_client-0.0.4.dist-info/METADATA
spyder_remote_client-0.0.4.dist-info/WHEEL
spyder_remote_client-0.0.4.dist-info/entry_points.txt
spyder_remote_client-0.0.4.dist-info/top_level.txt
spyder_remote_client-0.0.4.dist-info/RECORD
