Metadata-Version: 2.1
Name: spyder-remote-client
Version: 0.0.4
Summary: Spyder remote client to connect to Spyder kernels via zeroconf.
Home-page: https://github.com/Semi-ATE/spyder-remote/tree/master/spyder-remote-client
License: UNKNOWN
Platform: UNKNOWN
Requires-Dist: netifaces
Requires-Dist: psutil
Requires-Dist: spyder (>=5.0.1)
Requires-Dist: zeroconf (<=0.27)
